.coveragerc
.editorconfig
.gitattributes
.gitignore
.gitlab-ci.yml
AUTHORS.rst
CONTRIBUTING.rst
HISTORY.rst
LICENSE
MANIFEST.in
Makefile
README.rst
pyproject.toml
tox.ini
.github/ISSUE_TEMPLATE.md
docs/Makefile
docs/authors.rst
docs/conf.py
docs/contributing.rst
docs/history.rst
docs/index.rst
docs/installation.rst
docs/make.bat
docs/readme.rst
docs/usage.rst
docs/_build/html/_static/file.png
docs/_build/html/_static/minus.png
docs/_build/html/_static/plus.png
docs/_static/custom.css
py_tools_ds/__init__.py
py_tools_ds/version.py
py_tools_ds.egg-info/PKG-INFO
py_tools_ds.egg-info/SOURCES.txt
py_tools_ds.egg-info/dependency_links.txt
py_tools_ds.egg-info/not-zip-safe
py_tools_ds.egg-info/requires.txt
py_tools_ds.egg-info/top_level.txt
py_tools_ds/compression/__init__.py
py_tools_ds/compression/decompress.py
py_tools_ds/convenience/__init__.py
py_tools_ds/convenience/object_oriented.py
py_tools_ds/db_tools/__init__.py
py_tools_ds/db_tools/sql.py
py_tools_ds/dtypes/__init__.py
py_tools_ds/dtypes/conversion.py
py_tools_ds/environment/__init__.py
py_tools_ds/environment/gdal_env.py
py_tools_ds/geo/__init__.py
py_tools_ds/geo/coord_calc.py
py_tools_ds/geo/coord_grid.py
py_tools_ds/geo/coord_trafo.py
py_tools_ds/geo/map_info.py
py_tools_ds/geo/projection.py
py_tools_ds/geo/raster/__init__.py
py_tools_ds/geo/raster/conversion.py
py_tools_ds/geo/raster/reproject.py
py_tools_ds/geo/vector/__init__.py
py_tools_ds/geo/vector/conversion.py
py_tools_ds/geo/vector/geometry.py
py_tools_ds/geo/vector/topology.py
py_tools_ds/io/__init__.py
py_tools_ds/io/pathgen.py
py_tools_ds/io/raster/__init__.py
py_tools_ds/io/raster/gdal.py
py_tools_ds/io/raster/reader.py
py_tools_ds/io/raster/writer.py
py_tools_ds/io/vector/__init__.py
py_tools_ds/io/vector/writer.py
py_tools_ds/numeric/__init__.py
py_tools_ds/numeric/array.py
py_tools_ds/numeric/numbers.py
py_tools_ds/numeric/vector.py
py_tools_ds/processing/__init__.py
py_tools_ds/processing/progress_mon.py
py_tools_ds/processing/shell.py
py_tools_ds/web/__init__.py
py_tools_ds/web/network.py