Metadata-Version: 2.4
Name: py_tools_ds
Version: 0.23.3
Summary: A collection of Python tools by Daniel Scheffler
Author-email: Daniel Scheffler <daniel.scheffler@gfz-potsdam.de>
License-Expression: Apache-2.0
Project-URL: Homepage, https://git.gfz-potsdam.de/danschef/py_tools_ds
Keywords: py_tools_ds
Classifier: Development Status :: 4 - Beta
Classifier: Intended Audience :: Developers
Classifier: Natural Language :: English
Classifier: Programming Language :: Python :: 3
Classifier: Programming Language :: Python :: 3.8
Classifier: Programming Language :: Python :: 3.9
Classifier: Programming Language :: Python :: 3.10
Classifier: Programming Language :: Python :: 3.11
Classifier: Programming Language :: Python :: 3.12
Requires-Python: >=3.8
License-File: LICENSE
License-File: AUTHORS.rst
Requires-Dist: gdal>=3.8
Requires-Dist: numpy
Requires-Dist: pandas
Requires-Dist: pyproj>=2.5.0
Requires-Dist: shapely
Requires-Dist: spectral
Provides-Extra: rio-reproject
Requires-Dist: rasterio; extra == "rio-reproject"
Provides-Extra: doc
Requires-Dist: sphinx-argparse; extra == "doc"
Requires-Dist: sphinx_rtd_theme; extra == "doc"
Provides-Extra: test
Requires-Dist: gdal; extra == "test"
Requires-Dist: pytest; extra == "test"
Requires-Dist: pytest-cov; extra == "test"
Requires-Dist: pytest-reporter-html1; extra == "test"
Requires-Dist: urlchecker; extra == "test"
Provides-Extra: lint
Requires-Dist: flake8; extra == "lint"
Requires-Dist: pycodestyle; extra == "lint"
Requires-Dist: pydocstyle; extra == "lint"
Provides-Extra: dev
Requires-Dist: py_tools_ds[test]; extra == "dev"
Requires-Dist: py_tools_ds[doc]; extra == "dev"
Requires-Dist: py_tools_ds[lint]; extra == "dev"
Dynamic: license-file
